deproto/__init__.py
deproto/cluster.py
deproto/node.py
deproto/protobuf.py
deproto/types.py
deproto-0.2.5.dist-info/LICENSE
deproto-0.2.5.dist-info/METADATA
deproto-0.2.5.dist-info/WHEEL
deproto-0.2.5.dist-info/top_level.txt
deproto-0.2.5.dist-info/RECORD
