Metadata-Version: 2.1
Name: deproto
Version: 0.2.5
Summary: A decoder for Google Maps protobuf format
Home-page: https://github.com/MrDebugger/deproto
Author: Ijaz Ur Rahim
Author-email: ijazkhan095@gmail.com
Maintainer: Ijaz Ur Rahim
Maintainer-email: ijazkhan095@gmail.com
Project-URL: Website, https://ijazurrahim.com
Project-URL: Source, https://github.com/MrDebugger/deproto
Classifier: Programming Language :: Python :: 3
Classifier: License :: OSI Approved :: MIT License
Classifier: Operating System :: OS Independent
Requires-Python: >=3.6
License-File: LICENSE
Provides-Extra: dev
Requires-Dist: pytest>=8.3.4; extra == "dev"
Requires-Dist: pytest-cov>=6.0.0; extra == "dev"
Requires-Dist: flake8>=7.1.1; extra == "dev"
Requires-Dist: black>=24.10.0; extra == "dev"
Requires-Dist: isort>=5.13.2; extra == "dev"
Requires-Dist: pre-commit>=4.0.1; extra == "dev"
